rpi_networking/__init__.py
rpi_networking/configuration.py
rpi_networking/hostname.py
rpi_networking/hotspot.py
rpi_networking/status.py
rpi_networking/tools.py
rpi_networking/wifi.py
rpi_networking-0.1.9.dist-info/LICENSE
rpi_networking-0.1.9.dist-info/METADATA
rpi_networking-0.1.9.dist-info/WHEEL
rpi_networking-0.1.9.dist-info/RECORD
